apicloudru/__init__.py
apicloudru/client.py
apicloudru/exceptions.py
apicloudru/models/__init__.py
apicloudru/models/base.py
apicloudru/models/fssp.py
apicloudru-0.1.3.dist-info/LICENSE
apicloudru-0.1.3.dist-info/METADATA
apicloudru-0.1.3.dist-info/WHEEL
apicloudru-0.1.3.dist-info/top_level.txt
apicloudru-0.1.3.dist-info/RECORD
